cachecade/__init__.py
cachecade/caching.py
cachecade-0.2.0.dist-info/METADATA
cachecade-0.2.0.dist-info/WHEEL
cachecade-0.2.0.dist-info/top_level.txt
cachecade-0.2.0.dist-info/RECORD
