Metadata-Version: 2.4
Name: cachecade
Version: 0.2.0
Summary: A flexible caching decorator for Flask that supports Replit, Redis, and in-memory storage.
Home-page: https://github.com/ppicazo/cachecade
Author: Your Name
Author-email: paul@picazo.com
Classifier: Programming Language :: Python :: 3
Classifier: License :: OSI Approved :: MIT License
Classifier: Operating System :: OS Independent
Requires-Python: >=3.6
Requires-Dist: Flask>=1.0
Requires-Dist: replit>=0.0.1
Provides-Extra: redis
Requires-Dist: redis>=3.5.3; extra == "redis"
Dynamic: author
Dynamic: author-email
Dynamic: classifier
Dynamic: description
Dynamic: description-content-type
Dynamic: home-page
Dynamic: provides-extra
Dynamic: requires-dist
Dynamic: requires-python
Dynamic: summary
